nMethods/__init__.py
nMethods/main.py
nMethods-0.1.0.dist-info/METADATA
nMethods-0.1.0.dist-info/WHEEL
nMethods-0.1.0.dist-info/top_level.txt
nMethods-0.1.0.dist-info/RECORD
