Metadata-Version: 2.1
Name: nMethods
Version: 0.1.0
Summary: UNKNOWN
Home-page: https://github.com/sub2pewdiepie/NumericMethods.git
License: UNKNOWN
Platform: UNKNOWN
Requires-Dist: numpy (==1.22.3)
